LICENCE
flake8_debugger.py
pyproject.toml
flake8_debugger-4.1.0.dist-info/entry_points.txt
flake8_debugger-4.1.0.dist-info/WHEEL
flake8_debugger-4.1.0.dist-info/METADATA
flake8_debugger-4.1.0.dist-info/RECORD
